{
    "appName": "flow",
    "roleName": "pinpointLambdaRole17d902ef",
    "cloudformationPolicyName": "cloudformationPolicy17d902ef",
    "cloudWatchPolicyName": "cloudWatchPolicy17d902ef",
    "pinpointPolicyName": "pinpointPolicy17d902ef",
    "authPolicyName": "pinpoint_amplify_17d902ef",
    "unauthPolicyName": "pinpoint_amplify_17d902ef",
    "authRoleName": {
        "Ref": "AuthRoleName"
    },
    "unauthRoleName": {
        "Ref": "UnauthRoleName"
    },
    "authRoleArn": {
        "Fn::GetAtt": [
            "AuthRole",
            "Arn"
        ]
    }
}